remove_sections.py
remove_sections-0.2.0.dist-info/licenses/LICENSE
remove_sections-0.2.0.dist-info/METADATA
remove_sections-0.2.0.dist-info/WHEEL
remove_sections-0.2.0.dist-info/entry_points.txt
remove_sections-0.2.0.dist-info/top_level.txt
remove_sections-0.2.0.dist-info/RECORD
