Metadata-Version: 2.4
Name: remove-sections
Version: 0.2.0
Summary: Remove sections from video files without re-encoding
Author-email: Lorenzo Wood <lorenzo@lorenzowood.com>
License: MIT
Project-URL: Homepage, https://github.com/lorenzowood/remove-sections
Project-URL: Repository, https://github.com/lorenzowood/remove-sections
Project-URL: Issues, https://github.com/lorenzowood/remove-sections/issues
Keywords: video,ffmpeg,editing,video-processing,command-line
Classifier: Development Status :: 4 - Beta
Classifier: Intended Audience :: End Users/Desktop
Classifier: License :: OSI Approved :: MIT License
Classifier: Operating System :: OS Independent
Classifier: Programming Language :: Python :: 3
Classifier: Programming Language :: Python :: 3.11
Classifier: Programming Language :: Python :: 3.12
Classifier: Topic :: Multimedia :: Video
Classifier: Topic :: Utilities
Requires-Python: >=3.11
License-File: LICENSE
Dynamic: license-file
